imgread_benchmark/__init__.py
imgread_benchmark/benchmark.py
imgread_benchmark/cl_app.py
imgread_benchmark/cl_versions.py
imgread_benchmark/get_img_filenames.py
imgread_benchmark/read_img.py
imgread_benchmark/version.py
imgread_benchmark/img_libs/PIL.py
imgread_benchmark/img_libs/__init__.py
imgread_benchmark/img_libs/accimage.py
imgread_benchmark/img_libs/convert.py
imgread_benchmark/img_libs/cv2.py
imgread_benchmark/img_libs/imageio.py
imgread_benchmark/img_libs/img_libs_pkgs.py
imgread_benchmark/img_libs/jpeg4py.py
imgread_benchmark/img_libs/kornia.py
imgread_benchmark/img_libs/pyvips.py
imgread_benchmark/img_libs/skimage.py
imgread_benchmark/img_libs/torchvision.py
imgread_benchmark-0.2.dist-info/LICENSE
imgread_benchmark-0.2.dist-info/METADATA
imgread_benchmark-0.2.dist-info/WHEEL
imgread_benchmark-0.2.dist-info/entry_points.txt
imgread_benchmark-0.2.dist-info/top_level.txt
imgread_benchmark-0.2.dist-info/RECORD
