Metadata-Version: 2.1
Name: imgread_benchmark
Version: 0.2
Summary: benchmark for read images.
Home-page: https://github.com/ayasyrev/imgread_benchmark
Author: Yasyrev Andrei
Author-email: a.yasyrev@gmail.com
License: apache2
Classifier: Programming Language :: Python :: 3
Classifier: Programming Language :: Python :: 3.8
Classifier: Programming Language :: Python :: 3.9
Classifier: Programming Language :: Python :: 3.10
Classifier: Programming Language :: Python :: 3.11
Classifier: Programming Language :: Python :: 3.12
Classifier: License :: OSI Approved :: Apache Software License
Classifier: Operating System :: OS Independent
License-File: LICENSE
Provides-Extra: test
Provides-Extra: dev
